eventmq/__init__.py
eventmq/conf.py
eventmq/constants.py
eventmq/exceptions.py
eventmq/jobmanager.py
eventmq/log.py
eventmq/poller.py
eventmq/pub.py
eventmq/publisher.py
eventmq/receiver.py
eventmq/router.py
eventmq/scheduler.py
eventmq/sender.py
eventmq/subscriber.py
eventmq/switch.py
eventmq/worker.py
eventmq/client/__init__.py
eventmq/client/jobs.py
eventmq/client/messages.py
eventmq/tests/__init__.py
eventmq/tests/test_client_jobs.py
eventmq/tests/test_client_messages.py
eventmq/tests/test_jobmanager.py
eventmq/tests/test_receiver.py
eventmq/tests/test_router.py
eventmq/tests/test_scheduler.py
eventmq/tests/test_sender.py
eventmq/tests/test_utils.py
eventmq/tests/test_utils_encoding.py
eventmq/tests/test_worker.py
eventmq/tests/utils.py
eventmq/utils/__init__.py
eventmq/utils/classes.py
eventmq/utils/devices.py
eventmq/utils/encoding.py
eventmq/utils/functions.py
eventmq/utils/messages.py
eventmq/utils/settings.py
eventmq/utils/timeutils.py
eventmq-0.3.13.data/scripts/emq-cli
eventmq-0.3.13.data/scripts/emq-jobmanager
eventmq-0.3.13.data/scripts/emq-pubsub
eventmq-0.3.13.data/scripts/emq-router
eventmq-0.3.13.data/scripts/emq-scheduler
eventmq-0.3.13.dist-info/LICENSE
eventmq-0.3.13.dist-info/METADATA
eventmq-0.3.13.dist-info/WHEEL
eventmq-0.3.13.dist-info/top_level.txt
eventmq-0.3.13.dist-info/RECORD
