Metadata-Version: 2.1
Name: eventmq
Version: 0.3.13
Summary: EventMQ job execution and messaging system based on ZeroMQ
Home-page: https://github.com/eventmq/eventmq/
Author: EventMQ Contributors
License: UNKNOWN
Platform: UNKNOWN
Classifier: Development Status :: 3 - Alpha
Classifier: Intended Audience :: Developers
Classifier: Topic :: System :: Distributed Computing
Classifier: License :: OSI Approved :: GNU Lesser General Public License v2 (LGPLv2)
Classifier: Operating System :: OS Independent
Classifier: Programming Language :: Python :: 2.7
Classifier: Programming Language :: Python :: 3.5
Classifier: Programming Language :: Python :: 3.6
Classifier: Programming Language :: Python :: 3.7
Classifier: Programming Language :: Python :: 3.8
Requires-Dist: pyzmq (==18.1.0)
Requires-Dist: six (<2,>=1.14)
Requires-Dist: monotonic (==0.4)
Requires-Dist: croniter (==0.3.10)
Requires-Dist: future (==0.15.2)
Requires-Dist: psutil (==5.6.6)
Provides-Extra: docs
Requires-Dist: Sphinx (==1.5.2) ; extra == 'docs'
Provides-Extra: testing
Requires-Dist: flake8 (==3.7.8) ; extra == 'testing'
Requires-Dist: flake8-import-order (==0.18.1) ; extra == 'testing'
Requires-Dist: flake8-print (==3.1.0) ; extra == 'testing'
Requires-Dist: coverage (==4.0.3) ; extra == 'testing'
Requires-Dist: testfixtures (==4.7.0) ; extra == 'testing'
Requires-Dist: freezegun (==0.3.7) ; extra == 'testing'
Requires-Dist: tl.testing (==0.5) ; extra == 'testing'
Requires-Dist: mock (==1.3.0) ; extra == 'testing'
